leancheck/__init__.py
leancheck-0.0.6.dist-info/licenses/LICENSE
leancheck-0.0.6.dist-info/METADATA
leancheck-0.0.6.dist-info/WHEEL
leancheck-0.0.6.dist-info/top_level.txt
leancheck-0.0.6.dist-info/RECORD
