Metadata-Version: 2.4
Name: leancheck
Version: 0.0.6
Summary: Enumerative property-based testing
Author-email: Rudy Matela <rudy@matela.com.br>
License-Expression: LGPL-2.1-or-later
Project-URL: Homepage, https://github.com/rudymatela/python-leancheck
Project-URL: Bug Tracker, https://github.com/rudymatela/python-leancheck/issues
Project-URL: Repository, https://github.com/rudymatela/python-leancheck.git
Project-URL: Documentation, https://leancheck.github.io/
Classifier: Development Status :: 3 - Alpha
Classifier: Topic :: Software Development :: Testing
Classifier: Intended Audience :: Developers
Classifier: Operating System :: OS Independent
Classifier: Programming Language :: Python
License-File: LICENSE
Dynamic: license-file
